{
    "type": "overgeared:fletching",
    "material": {
      "feather": {
        "item": "minecraft:feather"
      },
      "shaft": {
        "tag": "forge:rods/wooden"
      },
      "tip": {
        "item": "minecraft:obsidian"
      }
    },
    "result": {
        "count": 4,
        "item": "apotheosis:obsidian_arrow"
      },
      "result_lingering": {
        "count": 4,
        "item": "apotheosis:obsidian_arrow"
      },
      "result_tipped": {
        "count": 4,
        "item": "apotheosis:obsidian_arrow"
      }
}